sublist3r.py
subbrute/__init__.py
subbrute/names.txt
subbrute/resolvers.txt
subbrute/subbrute.py
Sublist3r_lib-1.0.1.dist-info/LICENSE
Sublist3r_lib-1.0.1.dist-info/METADATA
Sublist3r_lib-1.0.1.dist-info/WHEEL
Sublist3r_lib-1.0.1.dist-info/entry_points.txt
Sublist3r_lib-1.0.1.dist-info/top_level.txt
Sublist3r_lib-1.0.1.dist-info/RECORD
