Metadata-Version: 2.1
Name: Sublist3r-lib
Version: 1.0.1
Summary: Subdomains enumeration tool for penetration testers
Home-page: https://github.com/aboul3la/Sublist3r-lib
License: GPL-2.0
Keywords: subdomain dns detection
Platform: UNKNOWN
Classifier: Development Status :: 5 - Production/Stable
Classifier: Environment :: Console
Classifier: Intended Audience :: Information Technology
Classifier: Intended Audience :: System Administrators
Classifier: Intended Audience :: Telecommunications Industry
Classifier: License :: OSI Approved :: GNU General Public License v2 (GPLv2)
Classifier: Operating System :: POSIX :: Linux
Classifier: Programming Language :: Python
Classifier: Programming Language :: Python :: 2
Classifier: Programming Language :: Python :: 3
Classifier: Programming Language :: Python :: 2.7
Classifier: Programming Language :: Python :: 3.4
Classifier: Programming Language :: Python :: 3.5
Classifier: Programming Language :: Python :: 3.6
Classifier: Topic :: Security
Requires-Python: >=2.7
Requires-Dist: dnspython
Requires-Dist: requests
Requires-Dist: argparse ; python_version == "2.7"
